huaweicloudsdkwaf/__init__.py
huaweicloudsdkwaf/v1/__init__.py
huaweicloudsdkwaf/v1/waf_async_client.py
huaweicloudsdkwaf/v1/waf_client.py
huaweicloudsdkwaf/v1/model/__init__.py
huaweicloudsdkwaf/v1/model/access_progress.py
huaweicloudsdkwaf/v1/model/access_status_body.py
huaweicloudsdkwaf/v1/model/action.py
huaweicloudsdkwaf/v1/model/alert_notice_config.py
huaweicloudsdkwaf/v1/model/alert_notice_config_response.py
huaweicloudsdkwaf/v1/model/alter_waf_product_info.py
huaweicloudsdkwaf/v1/model/anti_tamper_rule_response_body.py
huaweicloudsdkwaf/v1/model/anticrawler_condition.py
huaweicloudsdkwaf/v1/model/anticrawler_rule.py
huaweicloudsdkwaf/v1/model/antileakage_map_response_body_leakagemap.py
huaweicloudsdkwaf/v1/model/antileakage_map_response_body_locale.py
huaweicloudsdkwaf/v1/model/apply_certificate_to_host_request.py
huaweicloudsdkwaf/v1/model/apply_certificate_to_host_request_body.py
huaweicloudsdkwaf/v1/model/apply_certificate_to_host_response.py
huaweicloudsdkwaf/v1/model/async_job_req_body.py
huaweicloudsdkwaf/v1/model/attack_action_count_item.py
huaweicloudsdkwaf/v1/model/attack_type_classification_item.py
huaweicloudsdkwaf/v1/model/attack_type_item.py
huaweicloudsdkwaf/v1/model/bacth_create_white_black_ip_rule_request_body.py
huaweicloudsdkwaf/v1/model/bandwidth_statistics_timeline_item.py
huaweicloudsdkwaf/v1/model/batch_create_anti_tamper_rule_request.py
huaweicloudsdkwaf/v1/model/batch_create_anti_tamper_rule_response.py
huaweicloudsdkwaf/v1/model/batch_create_anti_tamper_rules_request_body.py
huaweicloudsdkwaf/v1/model/batch_create_antileakage_rule_request.py
huaweicloudsdkwaf/v1/model/batch_create_antileakage_rule_request_body.py
huaweicloudsdkwaf/v1/model/batch_create_antileakage_rule_response.py
huaweicloudsdkwaf/v1/model/batch_create_cc_rule_request.py
huaweicloudsdkwaf/v1/model/batch_create_cc_rule_request_body.py
huaweicloudsdkwaf/v1/model/batch_create_cc_rule_response.py
huaweicloudsdkwaf/v1/model/batch_create_custom_rule_request.py
huaweicloudsdkwaf-3.1.184.dist-info/METADATA
huaweicloudsdkwaf-3.1.184.dist-info/WHEEL
huaweicloudsdkwaf-3.1.184.dist-info/licenses/LICENSE
huaweicloudsdkwaf-3.1.184.dist-info/RECORD
